cdklabs/generative_ai_cdk_constructs/__init__.py
cdklabs/generative_ai_cdk_constructs/py.typed
cdklabs/generative_ai_cdk_constructs/_jsii/__init__.py
cdklabs/generative_ai_cdk_constructs/_jsii/generative-ai-cdk-constructs@0.1.311.jsii.tgz
cdklabs/generative_ai_cdk_constructs/amazonaurora/__init__.py
cdklabs/generative_ai_cdk_constructs/aurora_dsql/__init__.py
cdklabs/generative_ai_cdk_constructs/bedrock/__init__.py
cdklabs/generative_ai_cdk_constructs/bedrock/pii_type/__init__.py
cdklabs/generative_ai_cdk_constructs/kendra/__init__.py
cdklabs/generative_ai_cdk_constructs/kendra/kendra/__init__.py
cdklabs/generative_ai_cdk_constructs/mongodb_atlas/__init__.py
cdklabs/generative_ai_cdk_constructs/neptune/__init__.py
cdklabs/generative_ai_cdk_constructs/opensearch_vectorindex/__init__.py
cdklabs/generative_ai_cdk_constructs/opensearchmanagedcluster/__init__.py
cdklabs/generative_ai_cdk_constructs/opensearchserverless/__init__.py
cdklabs/generative_ai_cdk_constructs/pinecone/__init__.py
cdklabs_generative_ai_cdk_constructs-0.1.311.dist-info/LICENSE
cdklabs_generative_ai_cdk_constructs-0.1.311.dist-info/METADATA
cdklabs_generative_ai_cdk_constructs-0.1.311.dist-info/NOTICE
cdklabs_generative_ai_cdk_constructs-0.1.311.dist-info/WHEEL
cdklabs_generative_ai_cdk_constructs-0.1.311.dist-info/top_level.txt
cdklabs_generative_ai_cdk_constructs-0.1.311.dist-info/RECORD
