Metadata-Version: 2.1
Name: cdklabs.generative-ai-cdk-constructs
Version: 0.1.311
Summary: AWS Generative AI CDK Constructs is a library for well-architected generative AI patterns.
Home-page: https://github.com/awslabs/generative-ai-cdk-constructs
Author: Amazon Web Services - Prototyping and Cloud Engineering
License: Apache-2.0
Project-URL: Source, https://github.com/awslabs/generative-ai-cdk-constructs
Classifier: Intended Audience :: Developers
Classifier: Operating System :: OS Independent
Classifier: Programming Language :: JavaScript
Classifier: Programming Language :: Python :: 3 :: Only
Classifier: Programming Language :: Python :: 3.9
Classifier: Programming Language :: Python :: 3.10
Classifier: Programming Language :: Python :: 3.11
Classifier: Typing :: Typed
Classifier: Development Status :: 4 - Beta
Classifier: License :: OSI Approved
Requires-Python: ~=3.9
License-File: LICENSE
License-File: NOTICE
Requires-Dist: aws-cdk-lib <3.0.0,>=2.219.0
Requires-Dist: cdk-nag <3.0.0,>=2.37.51
Requires-Dist: constructs <11.0.0,>=10.3.0
Requires-Dist: jsii <2.0.0,>=1.115.0
Requires-Dist: publication >=0.0.3
Requires-Dist: typeguard <4.3.0,>=2.13.3
